takanori_cli/__init__.py
takanori_cli/create.py
takanori_cli/main.py
takanori_cli/plugin.py
takanori_cli-1.0.0.dist-info/LICENSE
takanori_cli-1.0.0.dist-info/METADATA
takanori_cli-1.0.0.dist-info/WHEEL
takanori_cli-1.0.0.dist-info/entry_points.txt
takanori_cli-1.0.0.dist-info/top_level.txt
takanori_cli-1.0.0.dist-info/RECORD
