Metadata-Version: 2.1
Name: takanori-cli
Version: 1.0.0
Summary: Takanori commands for my automation tool.
Home-page: https://github.com/takavfx/takanori-cli
Author: Takanori Kishikawa
Author-email: auratus.lemma@gmail.com
Classifier: Programming Language :: Python
Classifier: Programming Language :: Python :: 3
Requires-Python: >=3.7
License-File: LICENSE
Requires-Dist: click
Requires-Dist: cookiecutter
